generalizit/__init__.py
generalizit/design.py
generalizit/design_utils.py
generalizit/g_theory_utils.py
generalizit/generalizit.py
generalizit-0.1.2.dist-info/licenses/LICENSE
generalizit-0.1.2.dist-info/METADATA
generalizit-0.1.2.dist-info/WHEEL
generalizit-0.1.2.dist-info/top_level.txt
generalizit-0.1.2.dist-info/RECORD
