Metadata-Version: 2.4
Name: generalizit
Version: 0.1.2
Summary: Generalizability theory fully crossed and nested
Author-email: Tyler Smith <tyler.js.smith111@gmail.com>
Project-URL: Issues, https://github.com/tylerjsmith111/GeneralizIT/issues
Project-URL: Homepage, https://github.com/tylerjsmith111/GeneralizIT
Project-URL: Documentation, https://github.com/tylerjsmith111/GeneralizIT#readme
Keywords: generalizability theory,classical test theory,unbalanced design
Classifier: Programming Language :: Python :: 3
Classifier: License :: OSI Approved :: MIT License
Classifier: Intended Audience :: Science/Research
Classifier: Operating System :: OS Independent
License-File: LICENSE
Requires-Dist: numpy>=1.21.0
Requires-Dist: pandas>=1.3.0
Requires-Dist: scipy>=1.7.0
Provides-Extra: test
Requires-Dist: pytest>=7.0; extra == "test"
Dynamic: license-file
